{
  "kind": "collectionType",
  "collectionName": "blog_posts",
  "info": {
    "singularName": "blog-post",
    "pluralName": "blog-posts",
    "displayName": "blog-posts"
  },
  "options": {
    "draftAndPublish": true
  },
  "pluginOptions": {},
  "attributes": {
    "title": {
      "type": "richtext"
    },
    "body": {
      "type": "richtext"
    },
    "headerImg": {
      "allowedTypes": [
        "images",
        "files",
        "videos",
        "audios"
      ],
      "type": "media",
      "multiple": false
    },
    "extraImgs": {
      "allowedTypes": [
        "images",
        "files",
        "videos",
        "audios"
      ],
      "type": "media",
      "multiple": true
    }
  }
}
